{
  "code": "100000",
  "msg": "succ",
  "data": {
    "Component_Play_Playinfo": {
      "mid": 5007452630158934,
      "id": "1034:5007449447661594",
      "oid": "1034:5007449447661594",
      "media_id": 5007449447661594,
      "user": {
        "id": 3110964661
      },
      "is_follow": false,
      "attitude": false,
      "date": "2年前",
      "real_date": 1709352445,
      "idstr": "1034:5007449447661594",
      "author": "小锋小志的猫咪小院",
      "author_id": 3110964661,
      "nickname": "小锋小志的猫咪小院",
      "verified": true,
      "verified_type": 0,
      "verified_type_ext": 1,
      "verified_reason": "萌宠博主 微博原创视频博主",
      "avatar": "//tvax4.sinaimg.cn/small/b96d8db5ly8hlx0ljomk9j20u00u0418.jpg?KID=imgbed,tva&Expires=1781284593&ssig=BSGW86mnhK",
      "followers_count": "99.8万",
      "reposts_count": "1,076",
      "comments_count": "3,069",
      "attitudes_count": 13682,
      "title": "再见，亲爱的咬咬小管家…",
      "urls": {
        "超清 2K60": "//f.video.weibocdn.com/o0/M1vsjZSmlx08cXYucm5i0104120r82OE0E0a0.mp4?label=mp4_1440p60&template=1440x2560.23.0&media_id=5007449447661594&tp=8x8A3El:YTkl0eM8&us=0&ori=1&bf=4&ot=v&ps=3lckmu&uid=3ZoTIp&ab=,8012-g2,3601-g32,3601-g31,8013-g0,3601-g29,3601-g39,3601-g36&Expires=1781277393&ssig=BlvX0mPJCq&KID=unistore,video",
        "高清 720P": "//f.video.weibocdn.com/o0/MU5PwbEglx08cXYmBv9u010412060Lrl0E030.mp4?label=mp4_720p&template=720x1280.24.0&media_id=5007449447661594&tp=8x8A3El:YTkl0eM8&us=0&ori=1&bf=4&ot=v&ps=3lckmu&uid=3ZoTIp&ab=,8012-g2,3601-g32,3601-g31,8013-g0,3601-g29,3601-g39,3601-g36&Expires=1781277393&ssig=mxNJ7v%2FurW&KID=unistore,video",
        "标清 480P": "//f.video.weibocdn.com/o0/J9sknzEFlx08cXYaDB8Y010412045hzx0E020.mp4?label=mp4_hd&template=540x960.26.0&media_id=5007449447661594&tp=8x8A3El:YTkl0eM8&us=0&ori=1&bf=4&ot=v&ps=3lckmu&uid=3ZoTIp&ab=,8012-g2,3601-g32,3601-g31,8013-g0,3601-g29,3601-g39,3601-g36&Expires=1781277393&ssig=DKC3AGBGbT&KID=unistore,video"
      },
      "cover_image": "//wx3.sinaimg.cn/orj480/b96d8db5ly1hnciqfntvkj20u01hc49x.jpg",
      "duration": "4:06",
      "duration_time": 246.3,
      "play_start": 0,
      "play_start_time": 0,
      "topics": [
        {
          "content": "猫咪小院的日常"
        },
        {
          "content": "猫咪小院"
        }
      ],
      "uuid": "5007450922025032",
      "text": "再见，亲爱的咬咬小管家…<a target=\"_blank\"  href=\"//s.weibo.com/weibo?q=%23%E7%8C%AB%E5%92%AA%E5%B0%8F%E9%99%A2%E7%9A%84%E6%97%A5%E5%B8%B8%23&from=default\">#猫咪小院的日常#</a><a target=\"_blank\"  href=\"//s.weibo.com/weibo?q=%23%E7%8C%AB%E5%92%AA%E5%B0%8F%E9%99%A2%23&from=default\">#猫咪小院#</a>  ​",
      "url_short": "http://t.cn/A6Y8UIAZ",
      "is_show_bulletin": 2,
      "comment_manage_info": {
        "comment_permission_type": -1,
        "approval_comment_type": 0,
        "comment_sort_type": 0
      },
      "video_orientation": "vertical",
      "is_contribution": 0,
      "live": false,
      "scrubber": [],
      "cooperate_video": 0,
      "is_pay_audio": 0,
      "is_paid": false,
      "display_duration": null,
      "gov_like_icon_data": null,
      "spotlights": null,
      "aigc_live_split": null,
      "manual_split": null,
      "drama_license": null,
      "stream_url": "http://f.video.weibocdn.com/o0/gBIgQDpqlx08cXYde7Zm01041202lC5I0E010.mp4?label=mp4_ld&template=360x640.24.0&ori=0&ps=IrBRQDE1x2Uj&Expires=1781277393&ssig=nlt4SDyfPC&KID=unistore,video",
      "object_type": "video",
      "play_count": "43.7万",
      "ip_info_str": "发布于 河南",
      "attitude_dynamic_adid": "",
      "user_video_count": 55,
      "allow_comment": false,
      "reward": {
        "version_state": 1,
        "state": 1,
        "welfare": 0,
        "desc": "点赞是美意，赞赏是鼓励",
        "reward_button_scheme": "https://reward.media.weibo.com/v1/public/h5/pay/reward?bid=1000303201&oid=5007452630158934&rewardsource=2&seller=3110964661&showmenu=0&topnavstyle=1&sign=e10a205544074fb35fcb0f2d417267e3",
        "reward_params": "bid=1000303201&oid=5007452630158934&rewardsource=2&seller=3110964661&showmenu=0&topnavstyle=1&sign=e10a205544074fb35fcb0f2d417267e3",
        "mid": "5007452630158934",
        "user": {
          "id": 3110964661,
          "idstr": "3110964661",
          "class": 1,
          "screen_name": "小锋小志的猫咪小院",
          "name": "小锋小志的猫咪小院",
          "province": "41",
          "city": "1000",
          "location": "河南",
          "description": "分享猫咪小院的快乐生活！每周六下午6点直播！ 咱们小院自己的品牌【泽囿zeyòu】 不接受送猫！拒绝爱心外包！道德绑架更是一巴掌！(ｰ̀дｰ́)",
          "url": "",
          "profile_image_url": "https://tvax4.sinaimg.cn/crop.0.0.1080.1080.50/b96d8db5ly8hlx0ljomk9j20u00u0418.jpg?KID=imgbed,tva&Expires=1781284593&ssig=BSGW86mnhK",
          "light_ring": false,
          "cover_image_phone": "https://wx1.sinaimg.cn/crop.0.0.640.640.640/b96d8db5ly1haao2vbk0fj20zu0zugst.jpg",
          "profile_url": "u/3110964661",
          "domain": "",
          "weihao": "",
          "gender": "m",
          "followers_count": 998388,
          "followers_count_str": "99.8万",
          "friends_count": 155,
          "pagefriends_count": 1,
          "statuses_count": 721,
          "video_status_count": 595,
          "video_play_count": 0,
          "super_topic_not_syn_count": 0,
          "favourites_count": 2,
          "created_at": "Sun Nov 11 11:26:17 +0800 2012",
          "following": false,
          "allow_all_act_msg": false,
          "geo_enabled": true,
          "verified": true,
          "verified_type": 0,
          "remark": "",
          "insecurity": {
            "sexual_content": false
          },
          "ptype": 0,
          "allow_all_comment": true,
          "avatar_large": "https://tvax4.sinaimg.cn/crop.0.0.1080.1080.180/b96d8db5ly8hlx0ljomk9j20u00u0418.jpg?KID=imgbed,tva&Expires=1781284593&ssig=DSMffCLu6%2B",
          "avatar_hd": "https://tvax4.sinaimg.cn/crop.0.0.1080.1080.1024/b96d8db5ly8hlx0ljomk9j20u00u0418.jpg?KID=imgbed,tva&Expires=1781284593&ssig=OCytLFHeSX",
          "verified_reason": "萌宠博主 微博原创视频博主",
          "verified_trade": "",
          "verified_reason_url": "",
          "verified_source": "",
          "verified_source_url": "",
          "verified_state": 0,
          "verified_level": 3,
          "verified_type_ext": 1,
          "has_service_tel": false,
          "verified_reason_modified": "",
          "verified_contact_name": "",
          "verified_contact_email": "",
          "verified_contact_mobile": "",
          "follow_me": false,
          "like": false,
          "like_me": false,
          "online_status": 0,
          "bi_followers_count": 121,
          "lang": "zh-cn",
          "star": 0,
          "mbtype": 12,
          "mbrank": 2,
          "svip": 1,
          "vvip": 1,
          "basic_member": 0,
          "mb_expire_time": 1786464000,
          "block_word": 0,
          "block_app": 1,
          "chaohua_ability": 0,
          "brand_ability": 0,
          "nft_ability": 0,
          "vplus_ability": 0,
          "wenda_ability": 0,
          "live_ability": 0,
          "gongyi_ability": 0,
          "paycolumn_ability": 0,
          "newbrand_ability": 0,
          "ecommerce_ability": 0,
          "hardfan_ability": 1,
          "wbcolumn_ability": 0,
          "interaction_user": 0,
          "audio_ability": 2,
          "place_ability": 1,
          "bluev_ad_ability": 0,
          "credit_score": 80,
          "user_ability": -2145122808,
          "avatargj_id": "gj_vip_011",
          "urank": 26,
          "story_read_state": -1,
          "verified_detail": {
            "custom": 0,
            "data": [
              {
                "key": 16,
                "sub_key": 1,
                "weight": 103,
                "desc": "微博原创视频博主",
                "timestamp": 0
              },
              {
                "key": 2,
                "sub_key": 0,
                "weight": 101,
                "desc": "萌宠博主",
                "timestamp": 0
              }
            ]
          },
          "vclub_member": 0,
          "is_teenager": 0,
          "is_guardian": 0,
          "is_teenager_list": 0,
          "pc_new": 0,
          "special_follow": false,
          "planet_video": 2,
          "video_mark": 2,
          "live_status": 0,
          "user_ability_extend": 10,
          "video_total_counter": {
            "play_cnt": 70476906
          },
          "brand_account": 0,
          "hongbaofei": 0,
          "green_mode": 0,
          "green_mode_source": 0,
          "delete_mode_time": 0,
          "urisk": 8796093022208,
          "unfollowing_recom_switch": 1,
          "block": 0,
          "block_me": 0,
          "avatar_type": 0,
          "is_big": 0,
          "auth_status": 4,
          "auth_realname": null,
          "auth_career": null,
          "auth_career_name": null,
          "show_auth": 0,
          "is_auth": 1,
          "is_punish": 0,
          "avatar_hd_pid": "b96d8db5ly8hlx0ljomk9j20u00u0418",
          "like_display": 0,
          "comment_display": 0
        }
      }
    }
  }
}
